README
setup.py
bin/knurko
knurko/__init__.py
knurko/cli.py
knurko/main.py
knurko/parse_mplayer.py
knurko/play.py
knurko.egg-info/PKG-INFO
knurko.egg-info/SOURCES.txt
knurko.egg-info/dependency_links.txt
knurko.egg-info/top_level.txt