Metadata-Version: 1.0
Name: knurko
Version: 0.1
Summary: Select a frame from a video file.
Home-page: http://small.dada.pink/knurko
Author: Thomas Levine
Author-email: _@thomaslevine.com
License: AGPL
Platform: UNKNOWN
